<?xml version='1.0' encoding='utf-8'?>
<patient><id>426_C</id><diagnosis>VTHR</diagnosis><measurement><start_time>1215</start_time><spectrum><frequency hz="0.5">4738.6</frequency><frequency hz="1.0">7.8642</frequency><frequency hz="1.5">198.66</frequency><frequency hz="2.0">249.66</frequency><frequency hz="2.5">57.947</frequency><frequency hz="3.0">30.137</frequency><frequency hz="3.5">37.907</frequency><frequency hz="4.0">34.159</frequency><frequency hz="4.5">536.31</frequency><frequency hz="5.0">2668.8</frequency><frequency hz="5.5">529.97</frequency><frequency hz="6.0">124.91</frequency><frequency hz="6.5">68.345</frequency><frequency hz="7.0">60.187</frequency><frequency hz="7.5">27.95</frequency><frequency hz="8.0">2.5615</frequency><frequency hz="8.5">12.768</frequency><frequency hz="9.0">45.193</frequency><frequency hz="9.5">7.0227</frequency><frequency hz="10.0">4.0249</frequency><frequency hz="10.5">0.044536</frequency><frequency hz="11.0">0.34277</frequency><frequency hz="11.5">1.3337</frequency><frequency hz="12.0">0.30936</frequency><frequency hz="12.5">0.10911</frequency><frequency hz="13.0">1.5514</frequency><frequency hz="13.5">0.71083</frequency><frequency hz="14.0">0.99083</frequency><frequency hz="14.5">0.095754</frequency><frequency hz="15.0">0.47005</frequency><frequency hz="15.5">0.40573</frequency><frequency hz="16.0">0.21343</frequency><frequency hz="16.5">0.083356</frequency><frequency hz="17.0">0.078739</frequency><frequency hz="17.5">0.55014</frequency><frequency hz="18.0">0.54935</frequency><frequency hz="18.5">0.0087722</frequency><frequency hz="19.0">0.021795</frequency><frequency hz="19.5">0.076549</frequency><frequency hz="20.0">0.04652</frequency><frequency hz="20.5">0.27975</frequency><frequency hz="21.0">0.066185</frequency><frequency hz="21.5">1.1063</frequency><frequency hz="22.0">1.3499</frequency><frequency hz="22.5">0.03714</frequency><frequency hz="23.0">0.19558</frequency><frequency hz="23.5">0.39234</frequency><frequency hz="24.0">1.0061</frequency><frequency hz="24.5">1.3172</frequency><frequency hz="25.0">0.72738</frequency><frequency hz="25.5">1.7746</frequency><frequency hz="26.0">1.741</frequency><frequency hz="26.5">0.46688</frequency><frequency hz="27.0">0.28321</frequency><frequency hz="27.5">1.0146</frequency><frequency hz="28.0">1.9849</frequency><frequency hz="28.5">1.7526</frequency><frequency hz="29.0">0.34329</frequency><frequency hz="29.5">0.29972</frequency><frequency hz="30.0">0.26227</frequency><frequency hz="30.5">0.65192</frequency><frequency hz="31.0">0.19553</frequency><frequency hz="31.5">0.4106</frequency><frequency hz="32.0">0.86702</frequency><frequency hz="32.5">0.62651</frequency><frequency hz="33.0">0.22011</frequency><frequency hz="33.5">0.0040072</frequency><frequency hz="34.0">0.020192</frequency><frequency hz="34.5">0.13008</frequency><frequency hz="35.0">0.053495</frequency><frequency hz="35.5">0.059473</frequency><frequency hz="36.0">0.12683</frequency><frequency hz="36.5">0.034659</frequency><frequency hz="37.0">0.027948</frequency><frequency hz="37.5">0.14828</frequency><frequency hz="38.0">0.046023</frequency><frequency hz="38.5">0.13464</frequency><frequency hz="39.0">0.035094</frequency><frequency hz="39.5">0.013429</frequency><frequency hz="40.0">0.12708</frequency><frequency hz="40.5">0.0991</frequency><frequency hz="41.0">0.042989</frequency><frequency hz="41.5">0.13028</frequency><frequency hz="42.0">0.017573</frequency><frequency hz="42.5">0.029958</frequency><frequency hz="43.0">0.009483</frequency><frequency hz="43.5">0.044431</frequency><frequency hz="44.0">2.236</frequency><frequency hz="44.5">1.8065</frequency><frequency hz="45.0">0.24801</frequency><frequency hz="45.5">0.36469</frequency><frequency hz="46.0">0.087978</frequency><frequency hz="46.5">0.03324</frequency><frequency hz="47.0">0.014524</frequency><frequency hz="47.5">0.017843</frequency><frequency hz="48.0">0.037366</frequency><frequency hz="48.5">0.013965</frequency><frequency hz="49.0">0.11851</frequency><frequency hz="49.5">0.11087</frequency><frequency hz="50.0">0.037665</frequency><frequency hz="50.5">0.049348</frequency><frequency hz="51.0">0.0080896</frequency><frequency hz="51.5">0.0024599</frequency><frequency hz="52.0">0.040718</frequency><frequency hz="52.5">0.0040336</frequency><frequency hz="53.0">0.051761</frequency><frequency hz="53.5">0.071766</frequency><frequency hz="54.0">0.0005314</frequency><frequency hz="54.5">0.0056857</frequency><frequency hz="55.0">0.00042215</frequency><frequency hz="55.5">0.0087513</frequency><frequency hz="56.0">0.0046899</frequency><frequency hz="56.5">0.0027469</frequency><frequency hz="57.0">0.011331</frequency><frequency hz="57.5">0.00018283</frequency><frequency hz="58.0">0.00019306</frequency><frequency hz="58.5">0.010796</frequency><frequency hz="59.0">0.014764</frequency><frequency hz="59.5">0.010322</frequency><frequency hz="60.0">0.0024664</frequency><frequency hz="60.5">7.7926e-05</frequency><frequency hz="61.0">0.0034186</frequency><frequency hz="61.5">0.0066384</frequency><frequency hz="62.0">0.0091985</frequency><frequency hz="62.5">0.012028</frequency><frequency hz="63.0">0.0065373</frequency><frequency hz="63.5">0.0067663</frequency><frequency hz="64.0">0.016807</frequency><frequency hz="64.5">0.0021296</frequency><frequency hz="65.0">0.0029162</frequency><frequency hz="65.5">9.3317e-05</frequency><frequency hz="66.0">0.00033554</frequency><frequency hz="66.5">0.0013938</frequency><frequency hz="67.0">0.001472</frequency><frequency hz="67.5">0.0021833</frequency><frequency hz="68.0">0.00095256</frequency><frequency hz="68.5">0.0013722</frequency><frequency hz="69.0">0.00015876</frequency><frequency hz="69.5">0.0030469</frequency><frequency hz="70.0">0.0024762</frequency><frequency hz="70.5">0.0036629</frequency><frequency hz="71.0">0.0027168</frequency><frequency hz="71.5">9.1503e-05</frequency><frequency hz="72.0">0.0013227</frequency><frequency hz="72.5">0.0038877</frequency><frequency hz="73.0">0.0028475</frequency><frequency hz="73.5">0.0021182</frequency><frequency hz="74.0">4.1951e-05</frequency><frequency hz="74.5">0.00095308</frequency><frequency hz="75.0">0.001918</frequency><frequency hz="75.5">0.00074649</frequency><frequency hz="76.0">0.00111</frequency><frequency hz="76.5">0.0043094</frequency><frequency hz="77.0">0.0018142</frequency><frequency hz="77.5">0.00023132</frequency><frequency hz="78.0">0.0010663</frequency><frequency hz="78.5">7.6019e-05</frequency><frequency hz="79.0">0.0010965</frequency><frequency hz="79.5">0.00024075</frequency><frequency hz="80.0">0.0003418</frequency><frequency hz="80.5">0.0012991</frequency><frequency hz="81.0">0.00039704</frequency><frequency hz="81.5">0.0012442</frequency><frequency hz="82.0">0.001127</frequency><frequency hz="82.5">0.00082749</frequency><frequency hz="83.0">0.00088828</frequency><frequency hz="83.5">0.00019745</frequency><frequency hz="84.0">0.00085274</frequency><frequency hz="84.5">0.00086945</frequency><frequency hz="85.0">0.00082283</frequency><frequency hz="85.5">0.00010465</frequency><frequency hz="86.0">0.00067862</frequency><frequency hz="86.5">8.2013e-05</frequency><frequency hz="87.0">0.0001015</frequency><frequency hz="87.5">0.0004185</frequency><frequency hz="88.0">4.9303e-06</frequency><frequency hz="88.5">0.0001123</frequency><frequency hz="89.0">0.00028042</frequency><frequency hz="89.5">4.7346e-05</frequency><frequency hz="90.0">0.00056288</frequency><frequency hz="90.5">9.8681e-05</frequency><frequency hz="91.0">5.8251e-05</frequency><frequency hz="91.5">0.0005286</frequency><frequency hz="92.0">0.00032004</frequency><frequency hz="92.5">0.0010157</frequency><frequency hz="93.0">0.00026682</frequency><frequency hz="93.5">0.00036917</frequency><frequency hz="94.0">0.00019928</frequency><frequency hz="94.5">4.9355e-05</frequency><frequency hz="95.0">0.00035446</frequency><frequency hz="95.5">0.00021073</frequency><frequency hz="96.0">0.00014458</frequency><frequency hz="96.5">7.0225e-05</frequency><frequency hz="97.0">4.0046e-05</frequency><frequency hz="97.5">0.00017775</frequency><frequency hz="98.0">0.00047889</frequency><frequency hz="98.5">4.7383e-05</frequency><frequency hz="99.0">0.00038045</frequency><frequency hz="99.5">2.1969e-05</frequency><frequency hz="100.0">0.00074541</frequency><frequency hz="100.5">0.00010666</frequency><frequency hz="101.0">0.00019764</frequency><frequency hz="101.5">4.8862e-06</frequency><frequency hz="102.0">0.00019273</frequency><frequency hz="102.5">0.00041537</frequency><frequency hz="103.0">0.00020036</frequency><frequency hz="103.5">0.00049745</frequency><frequency hz="104.0">1.4681e-05</frequency><frequency hz="104.5">0.00022253</frequency><frequency hz="105.0">0.00010289</frequency><frequency hz="105.5">0.00021906</frequency><frequency hz="106.0">0.00015543</frequency><frequency hz="106.5">0.00018058</frequency><frequency hz="107.0">0.00022581</frequency><frequency hz="107.5">0.00027868</frequency><frequency hz="108.0">0.00022221</frequency><frequency hz="108.5">0.00011691</frequency><frequency hz="109.0">0.00016119</frequency><frequency hz="109.5">0.00010068</frequency><frequency hz="110.0">0.00035062</frequency><frequency hz="110.5">6.14e-05</frequency><frequency hz="111.0">0.00056815</frequency><frequency hz="111.5">0.00012217</frequency><frequency hz="112.0">0.00020935</frequency><frequency hz="112.5">0.00031894</frequency><frequency hz="113.0">8.6352e-05</frequency><frequency hz="113.5">0.00017016</frequency><frequency hz="114.0">0.00026576</frequency><frequency hz="114.5">2.3033e-05</frequency><frequency hz="115.0">0.00018907</frequency><frequency hz="115.5">0.0005561</frequency><frequency hz="116.0">0.0022175</frequency><frequency hz="116.5">0.00045503</frequency><frequency hz="117.0">5.394e-05</frequency><frequency hz="117.5">1.2716e-05</frequency><frequency hz="118.0">0.00051583</frequency><frequency hz="118.5">1.4549e-05</frequency><frequency hz="119.0">8.4283e-05</frequency><frequency hz="119.5">0.00020116</frequency><frequency hz="120.0">9.5658e-05</frequency><frequency hz="120.5">0.0011234</frequency><frequency hz="121.0">0.00010825</frequency><frequency hz="121.5">0.00012522</frequency><frequency hz="122.0">6.3666e-06</frequency><frequency hz="122.5">0.00043048</frequency><frequency hz="123.0">0.00018899</frequency><frequency hz="123.5">0.00059951</frequency><frequency hz="124.0">3.0677e-05</frequency><frequency hz="124.5">0.00032155</frequency><frequency hz="125.0">0.00011985</frequency><frequency hz="125.5">8.554e-05</frequency><frequency hz="126.0">0.00024233</frequency><frequency hz="126.5">2.4388e-05</frequency><frequency hz="127.0">5.5034e-05</frequency><frequency hz="127.5">0.00020435</frequency><frequency hz="128.0">2.2232e-05</frequency><frequency hz="128.5">0.00049973</frequency><frequency hz="129.0">6.3978e-05</frequency><frequency hz="129.5">2.0288e-05</frequency><frequency hz="130.0">0.00029676</frequency><frequency hz="130.5">1.3981e-05</frequency><frequency hz="131.0">0.00014728</frequency><frequency hz="131.5">0.00015099</frequency><frequency hz="132.0">1.2359e-05</frequency><frequency hz="132.5">0.00044814</frequency><frequency hz="133.0">1.9923e-06</frequency><frequency hz="133.5">0.0001326</frequency><frequency hz="134.0">0.00019906</frequency><frequency hz="134.5">9.3449e-06</frequency><frequency hz="135.0">3.3144e-05</frequency><frequency hz="135.5">0.00049703</frequency><frequency hz="136.0">5.0823e-05</frequency><frequency hz="136.5">3.1708e-05</frequency><frequency hz="137.0">0.0002194</frequency><frequency hz="137.5">0.0001273</frequency><frequency hz="138.0">0.00023712</frequency><frequency hz="138.5">9.7783e-06</frequency><frequency hz="139.0">0.000337</frequency><frequency hz="139.5">7.2118e-05</frequency><frequency hz="140.0">8.2241e-05</frequency><frequency hz="140.5">3.2469e-05</frequency><frequency hz="141.0">3.7441e-05</frequency><frequency hz="141.5">2.9527e-05</frequency><frequency hz="142.0">0.00025525</frequency><frequency hz="142.5">6.3306e-06</frequency><frequency hz="143.0">0.0001174</frequency><frequency hz="143.5">5.2447e-05</frequency><frequency hz="144.0">1.8979e-05</frequency><frequency hz="144.5">0.00019943</frequency><frequency hz="145.0">8.1128e-05</frequency><frequency hz="145.5">0.00021411</frequency><frequency hz="146.0">0.00016667</frequency><frequency hz="146.5">6.292e-06</frequency><frequency hz="147.0">0.00027604</frequency><frequency hz="147.5">0.00017367</frequency><frequency hz="148.0">0.00013615</frequency><frequency hz="148.5">5.7877e-05</frequency><frequency hz="149.0">6.5e-05</frequency><frequency hz="149.5">9.4352e-05</frequency><frequency hz="150.0">3.581e-05</frequency><frequency hz="150.5">5.2531e-05</frequency><frequency hz="151.0">0.00013551</frequency><frequency hz="151.5">0.00017559</frequency><frequency hz="152.0">1.4469e-05</frequency><frequency hz="152.5">7.3854e-05</frequency><frequency hz="153.0">1.6377e-05</frequency><frequency hz="153.5">0.00026367</frequency><frequency hz="154.0">7.7032e-06</frequency><frequency hz="154.5">6.6086e-05</frequency><frequency hz="155.0">4.011e-05</frequency><frequency hz="155.5">3.9874e-05</frequency><frequency hz="156.0">4.2521e-05</frequency><frequency hz="156.5">0.00011588</frequency><frequency hz="157.0">0.00010516</frequency><frequency hz="157.5">7.4693e-05</frequency><frequency hz="158.0">4.9146e-05</frequency><frequency hz="158.5">9.3621e-05</frequency><frequency hz="159.0">1.0813e-05</frequency><frequency hz="159.5">3.3167e-05</frequency><frequency hz="160.0">0.00010942</frequency><frequency hz="160.5">7.7337e-05</frequency><frequency hz="161.0">4.3116e-05</frequency><frequency hz="161.5">0.00014576</frequency><frequency hz="162.0">4.4823e-05</frequency><frequency hz="162.5">8.4604e-06</frequency><frequency hz="163.0">0.00023578</frequency><frequency hz="163.5">1.4247e-06</frequency><frequency hz="164.0">2.8745e-05</frequency><frequency hz="164.5">0.00019605</frequency><frequency hz="165.0">1.0082e-05</frequency><frequency hz="165.5">2.9634e-06</frequency><frequency hz="166.0">0.0003634</frequency><frequency hz="166.5">5.814e-06</frequency><frequency hz="167.0">0.00010939</frequency><frequency hz="167.5">0.00022878</frequency><frequency hz="168.0">0.00014288</frequency><frequency hz="168.5">0.00031109</frequency><frequency hz="169.0">5.1671e-05</frequency><frequency hz="169.5">0.00029157</frequency><frequency hz="170.0">3.1152e-05</frequency><frequency hz="170.5">4.7182e-06</frequency><frequency hz="171.0">0.00015481</frequency><frequency hz="171.5">0.00019521</frequency><frequency hz="172.0">0.00025996</frequency><frequency hz="172.5">0.0001108</frequency><frequency hz="173.0">0.00027981</frequency><frequency hz="173.5">7.7826e-05</frequency><frequency hz="174.0">0.00037642</frequency><frequency hz="174.5">0.00040598</frequency><frequency hz="175.0">0.00024928</frequency><frequency hz="175.5">3.7271e-05</frequency><frequency hz="176.0">5.5236e-05</frequency><frequency hz="176.5">2.6461e-05</frequency><frequency hz="177.0">0.00020727</frequency><frequency hz="177.5">2.591e-06</frequency><frequency hz="178.0">0.00031217</frequency><frequency hz="178.5">6.4101e-05</frequency><frequency hz="179.0">8.3454e-05</frequency><frequency hz="179.5">1.2447e-05</frequency><frequency hz="180.0">0.00090656</frequency><frequency hz="180.5">6.1406e-05</frequency></spectrum></measurement></patient>