<?xml version='1.0' encoding='utf-8'?>
<patient><id>430_C</id><diagnosis>VTHR</diagnosis><measurement><start_time>1239s</start_time><spectrum><frequency hz="0.5">701.13</frequency><frequency hz="1.0">23.098</frequency><frequency hz="1.5">23.967</frequency><frequency hz="2.0">0.69389</frequency><frequency hz="2.5">2.2655</frequency><frequency hz="3.0">3.5786</frequency><frequency hz="3.5">2.4878</frequency><frequency hz="4.0">2.3516</frequency><frequency hz="4.5">1.4667</frequency><frequency hz="5.0">169.33</frequency><frequency hz="5.5">354.61</frequency><frequency hz="6.0">29.42</frequency><frequency hz="6.5">1.0857</frequency><frequency hz="7.0">2.0169</frequency><frequency hz="7.5">0.40803</frequency><frequency hz="8.0">0.036524</frequency><frequency hz="8.5">0.025878</frequency><frequency hz="9.0">2.6579</frequency><frequency hz="9.5">39.804</frequency><frequency hz="10.0">33.376</frequency><frequency hz="10.5">0.86876</frequency><frequency hz="11.0">0.098923</frequency><frequency hz="11.5">0.45081</frequency><frequency hz="12.0">0.21893</frequency><frequency hz="12.5">0.058401</frequency><frequency hz="13.0">0.0073713</frequency><frequency hz="13.5">0.084588</frequency><frequency hz="14.0">0.0021259</frequency><frequency hz="14.5">0.083129</frequency><frequency hz="15.0">0.27797</frequency><frequency hz="15.5">0.035204</frequency><frequency hz="16.0">0.035354</frequency><frequency hz="16.5">0.0072205</frequency><frequency hz="17.0">0.026175</frequency><frequency hz="17.5">0.042684</frequency><frequency hz="18.0">0.33278</frequency><frequency hz="18.5">1.85</frequency><frequency hz="19.0">0.32715</frequency><frequency hz="19.5">0.021989</frequency><frequency hz="20.0">0.0016194</frequency><frequency hz="20.5">0.0068183</frequency><frequency hz="21.0">0.058772</frequency><frequency hz="21.5">0.01151</frequency><frequency hz="22.0">0.026309</frequency><frequency hz="22.5">0.22843</frequency><frequency hz="23.0">0.21004</frequency><frequency hz="23.5">0.023428</frequency><frequency hz="24.0">0.028495</frequency><frequency hz="24.5">0.00062608</frequency><frequency hz="25.0">0.010309</frequency><frequency hz="25.5">0.0098083</frequency><frequency hz="26.0">0.0091187</frequency><frequency hz="26.5">0.040341</frequency><frequency hz="27.0">0.15543</frequency><frequency hz="27.5">0.04751</frequency><frequency hz="28.0">0.026438</frequency><frequency hz="28.5">0.031816</frequency><frequency hz="29.0">0.021645</frequency><frequency hz="29.5">0.057361</frequency><frequency hz="30.0">0.028863</frequency><frequency hz="30.5">0.026914</frequency><frequency hz="31.0">0.023076</frequency><frequency hz="31.5">0.21409</frequency><frequency hz="32.0">0.094311</frequency><frequency hz="32.5">0.0012675</frequency><frequency hz="33.0">0.016345</frequency><frequency hz="33.5">0.0081179</frequency><frequency hz="34.0">0.011307</frequency><frequency hz="34.5">0.0054553</frequency><frequency hz="35.0">0.0062889</frequency><frequency hz="35.5">0.043117</frequency><frequency hz="36.0">0.15271</frequency><frequency hz="36.5">0.048783</frequency><frequency hz="37.0">0.0017618</frequency><frequency hz="37.5">0.00074903</frequency><frequency hz="38.0">0.0095095</frequency><frequency hz="38.5">0.017555</frequency><frequency hz="39.0">0.018983</frequency><frequency hz="39.5">0.026795</frequency><frequency hz="40.0">0.0028702</frequency><frequency hz="40.5">0.037259</frequency><frequency hz="41.0">0.0029873</frequency><frequency hz="41.5">0.0030376</frequency><frequency hz="42.0">0.0001904</frequency><frequency hz="42.5">0.00065099</frequency><frequency hz="43.0">0.00021741</frequency><frequency hz="43.5">0.055186</frequency><frequency hz="44.0">1.159</frequency><frequency hz="44.5">0.36621</frequency><frequency hz="45.0">0.026635</frequency><frequency hz="45.5">0.0060487</frequency><frequency hz="46.0">0.0021661</frequency><frequency hz="46.5">0.00099294</frequency><frequency hz="47.0">0.014946</frequency><frequency hz="47.5">0.017179</frequency><frequency hz="48.0">0.0052396</frequency><frequency hz="48.5">0.0013246</frequency><frequency hz="49.0">0.0036288</frequency><frequency hz="49.5">0.0011636</frequency><frequency hz="50.0">0.014783</frequency><frequency hz="50.5">0.0053625</frequency><frequency hz="51.0">0.0001782</frequency><frequency hz="51.5">0.0052662</frequency><frequency hz="52.0">0.00090514</frequency><frequency hz="52.5">0.0014289</frequency><frequency hz="53.0">0.0074096</frequency><frequency hz="53.5">0.021745</frequency><frequency hz="54.0">0.0039373</frequency><frequency hz="54.5">0.0042023</frequency><frequency hz="55.0">0.001948</frequency><frequency hz="55.5">0.001475</frequency><frequency hz="56.0">0.0011913</frequency><frequency hz="56.5">0.00039444</frequency><frequency hz="57.0">0.0013805</frequency><frequency hz="57.5">0.0031127</frequency><frequency hz="58.0">0.0071404</frequency><frequency hz="58.5">0.0040958</frequency><frequency hz="59.0">0.00079724</frequency><frequency hz="59.5">0.0020272</frequency><frequency hz="60.0">0.00017801</frequency><frequency hz="60.5">0.00020627</frequency><frequency hz="61.0">0.0026062</frequency><frequency hz="61.5">0.00084518</frequency><frequency hz="62.0">0.0015733</frequency><frequency hz="62.5">0.0017259</frequency><frequency hz="63.0">0.00058215</frequency><frequency hz="63.5">0.0042152</frequency><frequency hz="64.0">0.0014575</frequency><frequency hz="64.5">0.0038721</frequency><frequency hz="65.0">0.003323</frequency><frequency hz="65.5">0.00044449</frequency><frequency hz="66.0">0.00035713</frequency><frequency hz="66.5">0.00073844</frequency><frequency hz="67.0">0.0047903</frequency><frequency hz="67.5">0.00047996</frequency><frequency hz="68.0">0.00013518</frequency><frequency hz="68.5">0.00021241</frequency><frequency hz="69.0">0.0024197</frequency><frequency hz="69.5">0.001905</frequency><frequency hz="70.0">0.0015728</frequency><frequency hz="70.5">0.00070926</frequency><frequency hz="71.0">0.00011027</frequency><frequency hz="71.5">0.0011132</frequency><frequency hz="72.0">0.00036351</frequency><frequency hz="72.5">0.0021363</frequency><frequency hz="73.0">0.00058254</frequency><frequency hz="73.5">0.00057144</frequency><frequency hz="74.0">0.00025216</frequency><frequency hz="74.5">0.0012702</frequency><frequency hz="75.0">1.3897e-05</frequency><frequency hz="75.5">0.00030119</frequency><frequency hz="76.0">0.00010835</frequency><frequency hz="76.5">7.8312e-05</frequency><frequency hz="77.0">0.00016438</frequency><frequency hz="77.5">0.00057734</frequency><frequency hz="78.0">6.5931e-05</frequency><frequency hz="78.5">0.00085968</frequency><frequency hz="79.0">0.00048751</frequency><frequency hz="79.5">0.00013948</frequency><frequency hz="80.0">0.0004752</frequency><frequency hz="80.5">0.00037008</frequency><frequency hz="81.0">5.7267e-05</frequency><frequency hz="81.5">0.00053212</frequency><frequency hz="82.0">0.00024191</frequency><frequency hz="82.5">0.00062043</frequency><frequency hz="83.0">0.00013103</frequency><frequency hz="83.5">8.1392e-05</frequency><frequency hz="84.0">0.00035719</frequency><frequency hz="84.5">0.00018997</frequency><frequency hz="85.0">9.7498e-05</frequency><frequency hz="85.5">6.2923e-05</frequency><frequency hz="86.0">0.00032107</frequency><frequency hz="86.5">1.5297e-05</frequency><frequency hz="87.0">0.00086242</frequency><frequency hz="87.5">4.4053e-05</frequency><frequency hz="88.0">0.00022967</frequency><frequency hz="88.5">0.00014924</frequency><frequency hz="89.0">0.0003224</frequency><frequency hz="89.5">0.00033798</frequency><frequency hz="90.0">4.2342e-05</frequency><frequency hz="90.5">0.00013975</frequency><frequency hz="91.0">9.6414e-05</frequency><frequency hz="91.5">7.2276e-05</frequency><frequency hz="92.0">0.00037442</frequency><frequency hz="92.5">0.0001362</frequency><frequency hz="93.0">1.7846e-05</frequency><frequency hz="93.5">0.0002992</frequency><frequency hz="94.0">8.4887e-05</frequency><frequency hz="94.5">0.00021664</frequency><frequency hz="95.0">7.6104e-05</frequency><frequency hz="95.5">0.00016146</frequency><frequency hz="96.0">8.0387e-05</frequency><frequency hz="96.5">0.00016003</frequency><frequency hz="97.0">0.00014152</frequency><frequency hz="97.5">4.9833e-05</frequency><frequency hz="98.0">0.00028756</frequency><frequency hz="98.5">4.7622e-06</frequency><frequency hz="99.0">0.00031028</frequency><frequency hz="99.5">2.4418e-05</frequency><frequency hz="100.0">0.00019044</frequency><frequency hz="100.5">0.00011639</frequency><frequency hz="101.0">0.00015614</frequency><frequency hz="101.5">0.00045793</frequency><frequency hz="102.0">5.9809e-06</frequency><frequency hz="102.5">0.00012893</frequency><frequency hz="103.0">4.7211e-05</frequency><frequency hz="103.5">0.00015043</frequency><frequency hz="104.0">0.0003854</frequency><frequency hz="104.5">9.346e-05</frequency><frequency hz="105.0">0.0003508</frequency><frequency hz="105.5">0.00020666</frequency><frequency hz="106.0">1.7992e-05</frequency><frequency hz="106.5">0.00028628</frequency><frequency hz="107.0">9.8146e-05</frequency><frequency hz="107.5">0.00025927</frequency><frequency hz="108.0">2.872e-05</frequency><frequency hz="108.5">2.2107e-05</frequency><frequency hz="109.0">0.00025339</frequency><frequency hz="109.5">9.9382e-05</frequency><frequency hz="110.0">0.00020709</frequency><frequency hz="110.5">1.6767e-05</frequency><frequency hz="111.0">0.00025257</frequency><frequency hz="111.5">0.00010658</frequency><frequency hz="112.0">4.7429e-05</frequency><frequency hz="112.5">0.00011043</frequency><frequency hz="113.0">0.0002358</frequency><frequency hz="113.5">4.5561e-05</frequency><frequency hz="114.0">6.9756e-05</frequency><frequency hz="114.5">0.00013153</frequency><frequency hz="115.0">0.00023482</frequency><frequency hz="115.5">3.6918e-06</frequency><frequency hz="116.0">0.00026728</frequency><frequency hz="116.5">0.00026322</frequency><frequency hz="117.0">6.4345e-05</frequency><frequency hz="117.5">8.0932e-06</frequency><frequency hz="118.0">0.00033119</frequency><frequency hz="118.5">7.5205e-05</frequency><frequency hz="119.0">3.8492e-05</frequency><frequency hz="119.5">5.2572e-05</frequency><frequency hz="120.0">9.0837e-05</frequency><frequency hz="120.5">0.00014453</frequency><frequency hz="121.0">7.1235e-05</frequency><frequency hz="121.5">5.4925e-05</frequency><frequency hz="122.0">6.4917e-05</frequency><frequency hz="122.5">0.00011342</frequency><frequency hz="123.0">7.1104e-05</frequency><frequency hz="123.5">4.2304e-05</frequency><frequency hz="124.0">0.00024981</frequency><frequency hz="124.5">1.3768e-05</frequency><frequency hz="125.0">0.00039051</frequency><frequency hz="125.5">2.676e-05</frequency><frequency hz="126.0">0.0001822</frequency><frequency hz="126.5">4.2669e-05</frequency><frequency hz="127.0">4.4698e-05</frequency><frequency hz="127.5">3.1236e-05</frequency><frequency hz="128.0">0.00028995</frequency><frequency hz="128.5">1.2473e-05</frequency><frequency hz="129.0">0.00026258</frequency><frequency hz="129.5">5.0698e-06</frequency><frequency hz="130.0">0.00018725</frequency><frequency hz="130.5">3.2636e-05</frequency><frequency hz="131.0">0.00027431</frequency><frequency hz="131.5">3.5546e-05</frequency><frequency hz="132.0">5.2783e-05</frequency><frequency hz="132.5">0.0003892</frequency><frequency hz="133.0">3.7377e-06</frequency><frequency hz="133.5">6.756e-05</frequency><frequency hz="134.0">0.00015198</frequency><frequency hz="134.5">7.8077e-05</frequency><frequency hz="135.0">0.00024763</frequency><frequency hz="135.5">1.4181e-05</frequency><frequency hz="136.0">0.00013892</frequency><frequency hz="136.5">4.6476e-05</frequency><frequency hz="137.0">0.0001557</frequency><frequency hz="137.5">6.5935e-05</frequency><frequency hz="138.0">1.8306e-06</frequency><frequency hz="138.5">0.00019833</frequency><frequency hz="139.0">7.4348e-05</frequency><frequency hz="139.5">6.7824e-05</frequency><frequency hz="140.0">3.3579e-05</frequency><frequency hz="140.5">0.00019614</frequency><frequency hz="141.0">8.724e-05</frequency><frequency hz="141.5">6.4237e-05</frequency><frequency hz="142.0">5.6308e-05</frequency><frequency hz="142.5">5.7077e-05</frequency><frequency hz="143.0">9.1796e-05</frequency><frequency hz="143.5">9.5591e-05</frequency><frequency hz="144.0">0.00011384</frequency><frequency hz="144.5">9.0106e-05</frequency><frequency hz="145.0">9.188e-06</frequency><frequency hz="145.5">0.00017557</frequency><frequency hz="146.0">1.8771e-05</frequency><frequency hz="146.5">0.00010384</frequency><frequency hz="147.0">0.0001222</frequency><frequency hz="147.5">7.4878e-05</frequency><frequency hz="148.0">7.6184e-05</frequency><frequency hz="148.5">3.9767e-05</frequency><frequency hz="149.0">7.2369e-05</frequency><frequency hz="149.5">4.9259e-05</frequency><frequency hz="150.0">6.2299e-05</frequency><frequency hz="150.5">7.3748e-05</frequency><frequency hz="151.0">0.00012618</frequency><frequency hz="151.5">1.6083e-05</frequency><frequency hz="152.0">0.00010072</frequency><frequency hz="152.5">5.0541e-05</frequency><frequency hz="153.0">2.6153e-05</frequency><frequency hz="153.5">0.0001477</frequency><frequency hz="154.0">4.4663e-05</frequency><frequency hz="154.5">3.2311e-05</frequency><frequency hz="155.0">0.00011321</frequency><frequency hz="155.5">3.562e-05</frequency><frequency hz="156.0">4.7505e-05</frequency><frequency hz="156.5">0.00014713</frequency><frequency hz="157.0">6.1815e-06</frequency><frequency hz="157.5">9.5312e-05</frequency><frequency hz="158.0">0.00013278</frequency><frequency hz="158.5">2.7166e-05</frequency><frequency hz="159.0">0.00013013</frequency><frequency hz="159.5">5.9732e-05</frequency><frequency hz="160.0">4.0309e-05</frequency><frequency hz="160.5">5.5748e-05</frequency><frequency hz="161.0">0.00010516</frequency><frequency hz="161.5">7.2009e-05</frequency><frequency hz="162.0">3.4884e-05</frequency><frequency hz="162.5">5.8753e-05</frequency><frequency hz="163.0">2.3749e-05</frequency><frequency hz="163.5">0.00017141</frequency><frequency hz="164.0">7.5526e-05</frequency><frequency hz="164.5">5.9585e-05</frequency><frequency hz="165.0">3.2516e-05</frequency><frequency hz="165.5">0.00015843</frequency><frequency hz="166.0">5.0574e-05</frequency><frequency hz="166.5">3.5737e-05</frequency><frequency hz="167.0">0.00015362</frequency><frequency hz="167.5">7.482e-05</frequency><frequency hz="168.0">0.00014976</frequency><frequency hz="168.5">1.7999e-05</frequency><frequency hz="169.0">0.00016109</frequency><frequency hz="169.5">3.324e-05</frequency><frequency hz="170.0">7.1262e-05</frequency><frequency hz="170.5">0.00010442</frequency><frequency hz="171.0">0.00012218</frequency><frequency hz="171.5">1.6364e-05</frequency><frequency hz="172.0">0.00012209</frequency><frequency hz="172.5">8.1099e-05</frequency><frequency hz="173.0">3.4568e-05</frequency><frequency hz="173.5">0.0010667</frequency><frequency hz="174.0">0.0001684</frequency><frequency hz="174.5">0.00016867</frequency><frequency hz="175.0">5.2512e-05</frequency><frequency hz="175.5">2.2871e-05</frequency><frequency hz="176.0">0.00025881</frequency><frequency hz="176.5">7.1315e-05</frequency><frequency hz="177.0">7.5328e-05</frequency><frequency hz="177.5">2.3361e-05</frequency><frequency hz="178.0">0.00014777</frequency><frequency hz="178.5">8.756e-05</frequency><frequency hz="179.0">4.0985e-05</frequency><frequency hz="179.5">5.8309e-05</frequency><frequency hz="180.0">9.4067e-05</frequency><frequency hz="180.5">6.0846e-07</frequency></spectrum></measurement></patient>